pyqtx/Qt.py
pyqtx/__init__.py
pyqtx/server_conn.py
pyqtx/xico.py
pyqtx/xsettings.py
pyqtx/xwidgets.py
pyqtx_widgets-0.1.2.data/scripts/pyqtx-demo.py
pyqtx_widgets-0.1.2.dist-info/METADATA
pyqtx_widgets-0.1.2.dist-info/WHEEL
pyqtx_widgets-0.1.2.dist-info/top_level.txt
pyqtx_widgets-0.1.2.dist-info/RECORD
