Metadata-Version: 2.1
Name: pyqtx-widgets
Version: 0.1.2
Summary: pyqtx Widgets
Home-page: https://pyqtx.gitlab.io/pyqtx_widgets/
Author: Pedro Morgan
Author-email: pete@daffodil.uk.com
License: UNKNOWN
Project-URL: Bug Tracker, https://gitlab.com/pyqtx/pyqtx_widgets/issues
Project-URL: Documentation, https://pyqtx.gitlab.io/pyqtx_widgets/
Project-URL: Source Code, https://gitlab.com/pyqtx/pyqtx_widgets
Platform: UNKNOWN
Classifier: Programming Language :: Python :: 3
Classifier: License :: OSI Approved :: GNU General Public License v2 (GPLv2)
Classifier: Operating System :: OS Independent
Requires-Python: >=3.4
Requires-Dist: mistune
Requires-Dist: qtawesome
